pythonbooknishi/__init__.py
pythonbooknishi/data/data_file
pythonbooknishi-1.0.1.dist-info/licenses/LICENSE.txt
pythonbooknishi-1.0.1.dist-info/METADATA
pythonbooknishi-1.0.1.dist-info/WHEEL
pythonbooknishi-1.0.1.dist-info/top_level.txt
pythonbooknishi-1.0.1.dist-info/RECORD
