Metadata-Version: 2.4
Name: pythonbooknishi
Version: 1.0.1
Summary: This is a test package for me.
Home-page: https://github.com/RyosukeNishi/pythonbooknishi
Author: ryosuke nishi
Author-email: ryosuke.nishi@gmail.com
Classifier: License :: OSI Approved :: MIT License
Classifier: Programming Language :: Python :: 3
Classifier: Programming Language :: Python :: 3.6
Classifier: Programming Language :: Python :: 3.7
Classifier: Programming Language :: Python :: 3.8
Classifier: Operating System :: OS Independent
Requires-Python: ~=3.6
License-File: LICENSE.txt
Requires-Dist: Click~=7.0
Provides-Extra: s3
Requires-Dist: boto3~=1.10.0; extra == "s3"
Provides-Extra: gcs
Requires-Dist: google-cloud-storage~=1.23.0; extra == "gcs"
Dynamic: author
Dynamic: author-email
Dynamic: classifier
Dynamic: description
Dynamic: description-content-type
Dynamic: home-page
Dynamic: license-file
Dynamic: provides-extra
Dynamic: requires-dist
Dynamic: requires-python
Dynamic: summary
